altprint/__init__.py
altprint/baseprints.py
altprint/core.py
altprint/flow.py
altprint/gcode.py
altprint/imports/__init__.py
altprint/imports/stl.py
altprint/path/__init__.py
altprint/path/complete_fill.py
altprint/path/lineutil.py
altprint/path/rectilinear_fill.py
altprint/path/rectilinear_optimal.py
altprint-0.1.2.dist-info/LICENSE
altprint-0.1.2.dist-info/METADATA
altprint-0.1.2.dist-info/WHEEL
altprint-0.1.2.dist-info/top_level.txt
altprint-0.1.2.dist-info/RECORD
