Metadata-Version: 2.1
Name: altprint
Version: 0.1.2
Summary: Alternative 3d printing
Home-page: https://github.com/couto0/altprint
Author: couto0
Author-email: daniel.couto64@gmail.com
License: UNKNOWN
Keywords: FFF FDM 3dprinting slicer slicing gcode
Platform: UNKNOWN
Classifier: Programming Language :: Python :: 3
Classifier: License :: OSI Approved :: GNU General Public License v2 (GPLv2)
Classifier: Operating System :: OS Independent
Requires-Python: >=3.6
License-File: LICENSE
Requires-Dist: numpy (>=1.19.4)
Requires-Dist: Shapely (>=1.7.1)
Requires-Dist: trimesh (>=3.9.1)
Requires-Dist: PuLP (>=2.4)
Requires-Dist: scipy (>=1.7.0)
Requires-Dist: networkx (>=2.5.1)
Requires-Dist: rtree (>=0.9.7)
